dbgorilla/__init__.py
dbgorilla/main.py
dbgorilla-0.0.1.dist-info/METADATA
dbgorilla-0.0.1.dist-info/WHEEL
dbgorilla-0.0.1.dist-info/licenses/LICENSE
dbgorilla-0.0.1.dist-info/RECORD
