Metadata-Version: 2.3
Name: dbgorilla
Version: 0.0.1
Summary: DBGorilla Python Client
Project-URL: Homepage, https://github.com/furiousengineering/dbgorilla-python-client
Author-email: Furious Engineering <devops@furiousengineering.com>
Classifier: License :: OSI Approved :: MIT License
Classifier: Operating System :: OS Independent
Classifier: Programming Language :: Python :: 3
Requires-Python: >=3.8
